{
  "year": 1581,
  "label": "1581 CE",
  "region_set": "early_modern",
  "era_summary": "1581 (MDLXXXI) was a common year starting on Sunday in the Julian calendar, and a common year starting on Thursday in the Proleptic Gregorian calendar.",
  "regions": {
    "rome_italy": {
      "score": 87,
      "summary": "Brecke records no major conflicts touching this region in 1581 (safety scored at the era baseline of 85). No Maddison GDP coverage for this region — economy held at neutral 50, reflecting the thin pre-modern record outside the European core. Governance held at neutral (V-Dem coverage starts 1789).",
      "factors": {
        "safety": 85,
        "health": 45,
        "economy": 50,
        "governance": 50,
        "religious_tolerance": 50
      },
      "factor_sources": {
        "safety": "brecke",
        "health": "baseline",
        "economy": "neutral",
        "governance": "neutral",
        "religious_tolerance": "neutral"
      },
      "sources": [
        {
          "label": "Wikipedia — 1581",
          "url": "https://en.wikipedia.org/wiki/1581"
        }
      ],
      "ruler": null,
      "sparse_data": true,
      "raw_score": 60
    },
    "andalusia_iberia": {
      "score": 1,
      "summary": "Active conflicts in 1581: Netherlands-Spain, 1566-1609; Portugal-Malabar, 1575-85; Spain-Netherlands (with intervention from France and England), 1578-1587. Maddison records GDP/capita 1279 (ESP, 1581) — used as the economy proxy for the whole region. Governance held at neutral (V-Dem coverage starts 1789).",
      "factors": {
        "safety": 5,
        "health": 45,
        "economy": 34,
        "governance": 50,
        "religious_tolerance": 50
      },
      "factor_sources": {
        "safety": "brecke",
        "health": "baseline",
        "economy": "maddison",
        "governance": "neutral",
        "religious_tolerance": "neutral"
      },
      "sources": [
        {
          "label": "Brecke Conflict Catalog 1400-2000",
          "url": "https://brecke.inta.gatech.edu/research/conflict/"
        },
        {
          "label": "Maddison Project 2023 — ESP 1581 gdppc=1279",
          "url": "https://www.rug.nl/ggdc/historicaldevelopment/maddison/releases/maddison-project-database-2023"
        },
        {
          "label": "Wikipedia — 1581",
          "url": "https://en.wikipedia.org/wiki/1581"
        }
      ],
      "ruler": null,
      "sparse_data": true,
      "raw_score": 33
    },
    "francia": {
      "score": 78,
      "summary": "Active conflicts in 1581: Netherlands-Spain, 1566-1609; Spain-Netherlands (with intervention from France and England), 1578-1587. Maddison records GDP/capita 3433 (NLD, 1581) — used as the economy proxy for the whole region. Governance held at neutral (V-Dem coverage starts 1789).",
      "factors": {
        "safety": 48,
        "health": 45,
        "economy": 90,
        "governance": 50,
        "religious_tolerance": 50
      },
      "factor_sources": {
        "safety": "brecke",
        "health": "baseline",
        "economy": "maddison",
        "governance": "neutral",
        "religious_tolerance": "neutral"
      },
      "sources": [
        {
          "label": "Brecke Conflict Catalog 1400-2000",
          "url": "https://brecke.inta.gatech.edu/research/conflict/"
        },
        {
          "label": "Maddison Project 2023 — NLD 1581 gdppc=3433",
          "url": "https://www.rug.nl/ggdc/historicaldevelopment/maddison/releases/maddison-project-database-2023"
        },
        {
          "label": "Wikipedia — 1581",
          "url": "https://en.wikipedia.org/wiki/1581"
        }
      ],
      "ruler": null,
      "sparse_data": true,
      "raw_score": 57
    },
    "england": {
      "score": 84,
      "summary": "Active conflicts in 1581: England-Munster (southern Ireland), 1569-83; Spain-Netherlands (with intervention from France and England), 1578-1587. Maddison records GDP/capita 1654 (GBR, 1581) — used as the economy proxy for the whole region. Governance held at neutral (V-Dem coverage starts 1789).",
      "factors": {
        "safety": 61,
        "health": 45,
        "economy": 81,
        "governance": 50,
        "religious_tolerance": 50
      },
      "factor_sources": {
        "safety": "brecke",
        "health": "baseline",
        "economy": "maddison",
        "governance": "neutral",
        "religious_tolerance": "neutral"
      },
      "sources": [
        {
          "label": "Brecke Conflict Catalog 1400-2000",
          "url": "https://brecke.inta.gatech.edu/research/conflict/"
        },
        {
          "label": "Maddison Project 2023 — GBR 1581 gdppc=1654",
          "url": "https://www.rug.nl/ggdc/historicaldevelopment/maddison/releases/maddison-project-database-2023"
        },
        {
          "label": "Wikipedia — 1581",
          "url": "https://en.wikipedia.org/wiki/1581"
        }
      ],
      "ruler": null,
      "sparse_data": true,
      "raw_score": 59
    },
    "rus": {
      "score": 39,
      "summary": "Active conflicts in 1581: Russia-Sweden, 1572-83; Poland-Russia, Livonia, Estonia, 1577-82; Muscovy-Siberian Tartars, 1578-81. No Maddison GDP coverage for this region — economy held at neutral 50, reflecting the thin pre-modern record outside the European core. Governance held at neutral (V-Dem coverage starts 1789).",
      "factors": {
        "safety": 37,
        "health": 45,
        "economy": 50,
        "governance": 50,
        "religious_tolerance": 50
      },
      "factor_sources": {
        "safety": "brecke",
        "health": "baseline",
        "economy": "neutral",
        "governance": "neutral",
        "religious_tolerance": "neutral"
      },
      "sources": [
        {
          "label": "Brecke Conflict Catalog 1400-2000",
          "url": "https://brecke.inta.gatech.edu/research/conflict/"
        },
        {
          "label": "Wikipedia — 1581",
          "url": "https://en.wikipedia.org/wiki/1581"
        }
      ],
      "ruler": null,
      "sparse_data": true,
      "raw_score": 45
    },
    "constantinople_balkans": {
      "score": 52,
      "summary": "Active conflicts in 1581: Emperor-Turkey, 1576-83; Turkey-Persia, 1578-90; Ethiopia-Turkey, 1578-89. No Maddison GDP coverage for this region — economy held at neutral 50, reflecting the thin pre-modern record outside the European core. Governance held at neutral (V-Dem coverage starts 1789).",
      "factors": {
        "safety": 49,
        "health": 45,
        "economy": 50,
        "governance": 50,
        "religious_tolerance": 50
      },
      "factor_sources": {
        "safety": "brecke",
        "health": "baseline",
        "economy": "neutral",
        "governance": "neutral",
        "religious_tolerance": "neutral"
      },
      "sources": [
        {
          "label": "Brecke Conflict Catalog 1400-2000",
          "url": "https://brecke.inta.gatech.edu/research/conflict/"
        },
        {
          "label": "Wikipedia — 1581",
          "url": "https://en.wikipedia.org/wiki/1581"
        }
      ],
      "ruler": null,
      "sparse_data": true,
      "raw_score": 49
    },
    "persia": {
      "score": 65,
      "summary": "Active conflicts in 1581: Turkey-Persia, 1578-90; Moguls-Afghanistan, 1581. No Maddison GDP coverage for this region — economy held at neutral 50, reflecting the thin pre-modern record outside the European core. Governance held at neutral (V-Dem coverage starts 1789).",
      "factors": {
        "safety": 61,
        "health": 45,
        "economy": 50,
        "governance": 50,
        "religious_tolerance": 50
      },
      "factor_sources": {
        "safety": "brecke",
        "health": "baseline",
        "economy": "neutral",
        "governance": "neutral",
        "religious_tolerance": "neutral"
      },
      "sources": [
        {
          "label": "Brecke Conflict Catalog 1400-2000",
          "url": "https://brecke.inta.gatech.edu/research/conflict/"
        },
        {
          "label": "Wikipedia — 1581",
          "url": "https://en.wikipedia.org/wiki/1581"
        }
      ],
      "ruler": null,
      "sparse_data": true,
      "raw_score": 53
    },
    "central_asia": {
      "score": 52,
      "summary": "Active conflicts in 1581: Japan (Chukoku area), 1577-82; Japan (warlords in Takaamakami ), 1580-82; China (Tartars in Liaoning), 1581-83. No Maddison GDP coverage for this region — economy held at neutral 50, reflecting the thin pre-modern record outside the European core. Governance held at neutral (V-Dem coverage starts 1789).",
      "factors": {
        "safety": 49,
        "health": 45,
        "economy": 50,
        "governance": 50,
        "religious_tolerance": 50
      },
      "factor_sources": {
        "safety": "brecke",
        "health": "baseline",
        "economy": "neutral",
        "governance": "neutral",
        "religious_tolerance": "neutral"
      },
      "sources": [
        {
          "label": "Brecke Conflict Catalog 1400-2000",
          "url": "https://brecke.inta.gatech.edu/research/conflict/"
        },
        {
          "label": "Wikipedia — 1581",
          "url": "https://en.wikipedia.org/wiki/1581"
        }
      ],
      "ruler": null,
      "sparse_data": true,
      "raw_score": 49
    },
    "egypt_nile": {
      "score": 87,
      "summary": "Brecke records no major conflicts touching this region in 1581 (safety scored at the era baseline of 85). No Maddison GDP coverage for this region — economy held at neutral 50, reflecting the thin pre-modern record outside the European core. Governance held at neutral (V-Dem coverage starts 1789).",
      "factors": {
        "safety": 85,
        "health": 45,
        "economy": 50,
        "governance": 50,
        "religious_tolerance": 50
      },
      "factor_sources": {
        "safety": "brecke",
        "health": "baseline",
        "economy": "neutral",
        "governance": "neutral",
        "religious_tolerance": "neutral"
      },
      "sources": [
        {
          "label": "Wikipedia — 1581",
          "url": "https://en.wikipedia.org/wiki/1581"
        }
      ],
      "ruler": null,
      "sparse_data": true,
      "raw_score": 60
    },
    "arabia": {
      "score": 74,
      "summary": "Active conflicts in 1581: Oman-Portugal (Muscat), 1581. No Maddison GDP coverage for this region — economy held at neutral 50, reflecting the thin pre-modern record outside the European core. Governance held at neutral (V-Dem coverage starts 1789).",
      "factors": {
        "safety": 73,
        "health": 45,
        "economy": 50,
        "governance": 50,
        "religious_tolerance": 50
      },
      "factor_sources": {
        "safety": "brecke",
        "health": "baseline",
        "economy": "neutral",
        "governance": "neutral",
        "religious_tolerance": "neutral"
      },
      "sources": [
        {
          "label": "Brecke Conflict Catalog 1400-2000",
          "url": "https://brecke.inta.gatech.edu/research/conflict/"
        },
        {
          "label": "Wikipedia — 1581",
          "url": "https://en.wikipedia.org/wiki/1581"
        }
      ],
      "ruler": null,
      "sparse_data": true,
      "raw_score": 56
    },
    "ethiopia": {
      "score": 74,
      "summary": "Active conflicts in 1581: Ethiopia-Turkey, 1578-89. No Maddison GDP coverage for this region — economy held at neutral 50, reflecting the thin pre-modern record outside the European core. Governance held at neutral (V-Dem coverage starts 1789).",
      "factors": {
        "safety": 73,
        "health": 45,
        "economy": 50,
        "governance": 50,
        "religious_tolerance": 50
      },
      "factor_sources": {
        "safety": "brecke",
        "health": "baseline",
        "economy": "neutral",
        "governance": "neutral",
        "religious_tolerance": "neutral"
      },
      "sources": [
        {
          "label": "Brecke Conflict Catalog 1400-2000",
          "url": "https://brecke.inta.gatech.edu/research/conflict/"
        },
        {
          "label": "Wikipedia — 1581",
          "url": "https://en.wikipedia.org/wiki/1581"
        }
      ],
      "ruler": null,
      "sparse_data": true,
      "raw_score": 56
    },
    "han_china": {
      "score": 74,
      "summary": "Active conflicts in 1581: China (Tartars in Liaoning), 1581-83. No Maddison GDP coverage for this region — economy held at neutral 50, reflecting the thin pre-modern record outside the European core. Governance held at neutral (V-Dem coverage starts 1789).",
      "factors": {
        "safety": 73,
        "health": 45,
        "economy": 50,
        "governance": 50,
        "religious_tolerance": 50
      },
      "factor_sources": {
        "safety": "brecke",
        "health": "baseline",
        "economy": "neutral",
        "governance": "neutral",
        "religious_tolerance": "neutral"
      },
      "sources": [
        {
          "label": "Brecke Conflict Catalog 1400-2000",
          "url": "https://brecke.inta.gatech.edu/research/conflict/"
        },
        {
          "label": "Wikipedia — 1581",
          "url": "https://en.wikipedia.org/wiki/1581"
        }
      ],
      "ruler": null,
      "sparse_data": true,
      "raw_score": 56
    },
    "japan": {
      "score": 65,
      "summary": "Active conflicts in 1581: Japan (Chukoku area), 1577-82; Japan (warlords in Takaamakami ), 1580-82. No Maddison GDP coverage for this region — economy held at neutral 50, reflecting the thin pre-modern record outside the European core. Governance held at neutral (V-Dem coverage starts 1789).",
      "factors": {
        "safety": 61,
        "health": 45,
        "economy": 50,
        "governance": 50,
        "religious_tolerance": 50
      },
      "factor_sources": {
        "safety": "brecke",
        "health": "baseline",
        "economy": "neutral",
        "governance": "neutral",
        "religious_tolerance": "neutral"
      },
      "sources": [
        {
          "label": "Brecke Conflict Catalog 1400-2000",
          "url": "https://brecke.inta.gatech.edu/research/conflict/"
        },
        {
          "label": "Wikipedia — 1581",
          "url": "https://en.wikipedia.org/wiki/1581"
        }
      ],
      "ruler": null,
      "sparse_data": true,
      "raw_score": 53
    },
    "north_america_east": {
      "score": 87,
      "summary": "Brecke records no major conflicts touching this region in 1581 (safety scored at the era baseline of 85). No Maddison GDP coverage for this region — economy held at neutral 50, reflecting the thin pre-modern record outside the European core. Governance held at neutral (V-Dem coverage starts 1789).",
      "factors": {
        "safety": 85,
        "health": 45,
        "economy": 50,
        "governance": 50,
        "religious_tolerance": 50
      },
      "factor_sources": {
        "safety": "brecke",
        "health": "baseline",
        "economy": "neutral",
        "governance": "neutral",
        "religious_tolerance": "neutral"
      },
      "sources": [
        {
          "label": "Wikipedia — 1581",
          "url": "https://en.wikipedia.org/wiki/1581"
        }
      ],
      "ruler": null,
      "sparse_data": true,
      "raw_score": 60
    },
    "andes": {
      "score": 87,
      "summary": "Brecke records no major conflicts touching this region in 1581 (safety scored at the era baseline of 85). No Maddison GDP coverage for this region — economy held at neutral 50, reflecting the thin pre-modern record outside the European core. Governance held at neutral (V-Dem coverage starts 1789).",
      "factors": {
        "safety": 85,
        "health": 45,
        "economy": 50,
        "governance": 50,
        "religious_tolerance": 50
      },
      "factor_sources": {
        "safety": "brecke",
        "health": "baseline",
        "economy": "neutral",
        "governance": "neutral",
        "religious_tolerance": "neutral"
      },
      "sources": [
        {
          "label": "Wikipedia — 1581",
          "url": "https://en.wikipedia.org/wiki/1581"
        }
      ],
      "ruler": null,
      "sparse_data": true,
      "raw_score": 60
    },
    "brazil_amazon": {
      "score": 87,
      "summary": "Brecke records no major conflicts touching this region in 1581 (safety scored at the era baseline of 85). No Maddison GDP coverage for this region — economy held at neutral 50, reflecting the thin pre-modern record outside the European core. Governance held at neutral (V-Dem coverage starts 1789).",
      "factors": {
        "safety": 85,
        "health": 45,
        "economy": 50,
        "governance": 50,
        "religious_tolerance": 50
      },
      "factor_sources": {
        "safety": "brecke",
        "health": "baseline",
        "economy": "neutral",
        "governance": "neutral",
        "religious_tolerance": "neutral"
      },
      "sources": [
        {
          "label": "Wikipedia — 1581",
          "url": "https://en.wikipedia.org/wiki/1581"
        }
      ],
      "ruler": null,
      "sparse_data": true,
      "raw_score": 60
    },
    "sweden_empire": {
      "score": 78,
      "summary": "Active conflicts in 1581: Russia-Sweden, 1572-83. Maddison records GDP/capita 1349 (SWE, 1581) — used as the economy proxy for the whole region. Governance held at neutral (V-Dem coverage starts 1789).",
      "factors": {
        "safety": 73,
        "health": 45,
        "economy": 53,
        "governance": 50,
        "religious_tolerance": 50
      },
      "factor_sources": {
        "safety": "brecke",
        "health": "baseline",
        "economy": "maddison",
        "governance": "neutral",
        "religious_tolerance": "neutral"
      },
      "sources": [
        {
          "label": "Brecke Conflict Catalog 1400-2000",
          "url": "https://brecke.inta.gatech.edu/research/conflict/"
        },
        {
          "label": "Maddison Project 2023 — SWE 1581 gdppc=1349",
          "url": "https://www.rug.nl/ggdc/historicaldevelopment/maddison/releases/maddison-project-database-2023"
        },
        {
          "label": "Wikipedia — 1581",
          "url": "https://en.wikipedia.org/wiki/1581"
        }
      ],
      "ruler": null,
      "sparse_data": true,
      "raw_score": 57
    },
    "denmark_norway": {
      "score": 87,
      "summary": "Brecke records no major conflicts touching this region in 1581 (safety scored at the era baseline of 85). No Maddison GDP coverage for this region — economy held at neutral 50, reflecting the thin pre-modern record outside the European core. Governance held at neutral (V-Dem coverage starts 1789).",
      "factors": {
        "safety": 85,
        "health": 45,
        "economy": 50,
        "governance": 50,
        "religious_tolerance": 50
      },
      "factor_sources": {
        "safety": "brecke",
        "health": "baseline",
        "economy": "neutral",
        "governance": "neutral",
        "religious_tolerance": "neutral"
      },
      "sources": [
        {
          "label": "Wikipedia — 1581",
          "url": "https://en.wikipedia.org/wiki/1581"
        }
      ],
      "ruler": null,
      "sparse_data": true,
      "raw_score": 60
    },
    "swedish_baltic": {
      "score": 74,
      "summary": "Active conflicts in 1581: Poland-Russia, Livonia, Estonia, 1577-82. No Maddison GDP coverage for this region — economy held at neutral 50, reflecting the thin pre-modern record outside the European core. Governance held at neutral (V-Dem coverage starts 1789).",
      "factors": {
        "safety": 73,
        "health": 45,
        "economy": 50,
        "governance": 50,
        "religious_tolerance": 50
      },
      "factor_sources": {
        "safety": "brecke",
        "health": "baseline",
        "economy": "neutral",
        "governance": "neutral",
        "religious_tolerance": "neutral"
      },
      "sources": [
        {
          "label": "Brecke Conflict Catalog 1400-2000",
          "url": "https://brecke.inta.gatech.edu/research/conflict/"
        },
        {
          "label": "Wikipedia — 1581",
          "url": "https://en.wikipedia.org/wiki/1581"
        }
      ],
      "ruler": null,
      "sparse_data": true,
      "raw_score": 56
    },
    "habsburg_austria": {
      "score": 87,
      "summary": "Brecke records no major conflicts touching this region in 1581 (safety scored at the era baseline of 85). No Maddison GDP coverage for this region — economy held at neutral 50, reflecting the thin pre-modern record outside the European core. Governance held at neutral (V-Dem coverage starts 1789).",
      "factors": {
        "safety": 85,
        "health": 45,
        "economy": 50,
        "governance": 50,
        "religious_tolerance": 50
      },
      "factor_sources": {
        "safety": "brecke",
        "health": "baseline",
        "economy": "neutral",
        "governance": "neutral",
        "religious_tolerance": "neutral"
      },
      "sources": [
        {
          "label": "Wikipedia — 1581",
          "url": "https://en.wikipedia.org/wiki/1581"
        }
      ],
      "ruler": null,
      "sparse_data": true,
      "raw_score": 60
    },
    "prussia_brandenburg": {
      "score": 100,
      "summary": "Brecke records no major conflicts touching this region in 1581 (safety scored at the era baseline of 85). Maddison records GDP/capita 1510 (DEU, 1581) — used as the economy proxy for the whole region. Governance held at neutral (V-Dem coverage starts 1789).",
      "factors": {
        "safety": 85,
        "health": 45,
        "economy": 71,
        "governance": 50,
        "religious_tolerance": 50
      },
      "factor_sources": {
        "safety": "brecke",
        "health": "baseline",
        "economy": "maddison",
        "governance": "neutral",
        "religious_tolerance": "neutral"
      },
      "sources": [
        {
          "label": "Maddison Project 2023 — DEU 1581 gdppc=1510",
          "url": "https://www.rug.nl/ggdc/historicaldevelopment/maddison/releases/maddison-project-database-2023"
        },
        {
          "label": "Wikipedia — 1581",
          "url": "https://en.wikipedia.org/wiki/1581"
        }
      ],
      "ruler": null,
      "sparse_data": true,
      "raw_score": 64
    },
    "german_princes": {
      "score": 100,
      "summary": "Brecke records no major conflicts touching this region in 1581 (safety scored at the era baseline of 85). Maddison records GDP/capita 1510 (DEU, 1581) — used as the economy proxy for the whole region. Governance held at neutral (V-Dem coverage starts 1789).",
      "factors": {
        "safety": 85,
        "health": 45,
        "economy": 71,
        "governance": 50,
        "religious_tolerance": 50
      },
      "factor_sources": {
        "safety": "brecke",
        "health": "baseline",
        "economy": "maddison",
        "governance": "neutral",
        "religious_tolerance": "neutral"
      },
      "sources": [
        {
          "label": "Maddison Project 2023 — DEU 1581 gdppc=1510",
          "url": "https://www.rug.nl/ggdc/historicaldevelopment/maddison/releases/maddison-project-database-2023"
        },
        {
          "label": "Wikipedia — 1581",
          "url": "https://en.wikipedia.org/wiki/1581"
        }
      ],
      "ruler": null,
      "sparse_data": true,
      "raw_score": 64
    },
    "polish_lithuanian_commonwealth": {
      "score": 71,
      "summary": "Active conflicts in 1581: Poland-Russia, Livonia, Estonia, 1577-82. Maddison records GDP/capita 1283 (POL, 1581) — used as the economy proxy for the whole region. Governance held at neutral (V-Dem coverage starts 1789).",
      "factors": {
        "safety": 73,
        "health": 45,
        "economy": 44,
        "governance": 50,
        "religious_tolerance": 50
      },
      "factor_sources": {
        "safety": "brecke",
        "health": "baseline",
        "economy": "maddison",
        "governance": "neutral",
        "religious_tolerance": "neutral"
      },
      "sources": [
        {
          "label": "Brecke Conflict Catalog 1400-2000",
          "url": "https://brecke.inta.gatech.edu/research/conflict/"
        },
        {
          "label": "Maddison Project 2023 — POL 1581 gdppc=1283",
          "url": "https://www.rug.nl/ggdc/historicaldevelopment/maddison/releases/maddison-project-database-2023"
        },
        {
          "label": "Wikipedia — 1581",
          "url": "https://en.wikipedia.org/wiki/1581"
        }
      ],
      "ruler": null,
      "sparse_data": true,
      "raw_score": 55
    },
    "mughal_north": {
      "score": 87,
      "summary": "Brecke records no major conflicts touching this region in 1581 (safety scored at the era baseline of 85). No Maddison GDP coverage for this region — economy held at neutral 50, reflecting the thin pre-modern record outside the European core. Governance held at neutral (V-Dem coverage starts 1789).",
      "factors": {
        "safety": 85,
        "health": 45,
        "economy": 50,
        "governance": 50,
        "religious_tolerance": 50
      },
      "factor_sources": {
        "safety": "brecke",
        "health": "baseline",
        "economy": "neutral",
        "governance": "neutral",
        "religious_tolerance": "neutral"
      },
      "sources": [
        {
          "label": "Wikipedia — 1581",
          "url": "https://en.wikipedia.org/wiki/1581"
        }
      ],
      "ruler": null,
      "sparse_data": true,
      "raw_score": 60
    },
    "maratha_confederacy": {
      "score": 87,
      "summary": "Brecke records no major conflicts touching this region in 1581 (safety scored at the era baseline of 85). No Maddison GDP coverage for this region — economy held at neutral 50, reflecting the thin pre-modern record outside the European core. Governance held at neutral (V-Dem coverage starts 1789).",
      "factors": {
        "safety": 85,
        "health": 45,
        "economy": 50,
        "governance": 50,
        "religious_tolerance": 50
      },
      "factor_sources": {
        "safety": "brecke",
        "health": "baseline",
        "economy": "neutral",
        "governance": "neutral",
        "religious_tolerance": "neutral"
      },
      "sources": [
        {
          "label": "Wikipedia — 1581",
          "url": "https://en.wikipedia.org/wiki/1581"
        }
      ],
      "ruler": null,
      "sparse_data": true,
      "raw_score": 60
    },
    "bengal": {
      "score": 87,
      "summary": "Brecke records no major conflicts touching this region in 1581 (safety scored at the era baseline of 85). No Maddison GDP coverage for this region — economy held at neutral 50, reflecting the thin pre-modern record outside the European core. Governance held at neutral (V-Dem coverage starts 1789).",
      "factors": {
        "safety": 85,
        "health": 45,
        "economy": 50,
        "governance": 50,
        "religious_tolerance": 50
      },
      "factor_sources": {
        "safety": "brecke",
        "health": "baseline",
        "economy": "neutral",
        "governance": "neutral",
        "religious_tolerance": "neutral"
      },
      "sources": [
        {
          "label": "Wikipedia — 1581",
          "url": "https://en.wikipedia.org/wiki/1581"
        }
      ],
      "ruler": null,
      "sparse_data": true,
      "raw_score": 60
    },
    "deccan_sultanates": {
      "score": 87,
      "summary": "Brecke records no major conflicts touching this region in 1581 (safety scored at the era baseline of 85). No Maddison GDP coverage for this region — economy held at neutral 50, reflecting the thin pre-modern record outside the European core. Governance held at neutral (V-Dem coverage starts 1789).",
      "factors": {
        "safety": 85,
        "health": 45,
        "economy": 50,
        "governance": 50,
        "religious_tolerance": 50
      },
      "factor_sources": {
        "safety": "brecke",
        "health": "baseline",
        "economy": "neutral",
        "governance": "neutral",
        "religious_tolerance": "neutral"
      },
      "sources": [
        {
          "label": "Wikipedia — 1581",
          "url": "https://en.wikipedia.org/wiki/1581"
        }
      ],
      "ruler": null,
      "sparse_data": true,
      "raw_score": 60
    },
    "voc_indonesia": {
      "score": 87,
      "summary": "Brecke records no major conflicts touching this region in 1581 (safety scored at the era baseline of 85). No Maddison GDP coverage for this region — economy held at neutral 50, reflecting the thin pre-modern record outside the European core. Governance held at neutral (V-Dem coverage starts 1789).",
      "factors": {
        "safety": 85,
        "health": 45,
        "economy": 50,
        "governance": 50,
        "religious_tolerance": 50
      },
      "factor_sources": {
        "safety": "brecke",
        "health": "baseline",
        "economy": "neutral",
        "governance": "neutral",
        "religious_tolerance": "neutral"
      },
      "sources": [
        {
          "label": "Wikipedia — 1581",
          "url": "https://en.wikipedia.org/wiki/1581"
        }
      ],
      "ruler": null,
      "sparse_data": true,
      "raw_score": 60
    },
    "siam_vietnam_burma": {
      "score": 87,
      "summary": "Brecke records no major conflicts touching this region in 1581 (safety scored at the era baseline of 85). No Maddison GDP coverage for this region — economy held at neutral 50, reflecting the thin pre-modern record outside the European core. Governance held at neutral (V-Dem coverage starts 1789).",
      "factors": {
        "safety": 85,
        "health": 45,
        "economy": 50,
        "governance": 50,
        "religious_tolerance": 50
      },
      "factor_sources": {
        "safety": "brecke",
        "health": "baseline",
        "economy": "neutral",
        "governance": "neutral",
        "religious_tolerance": "neutral"
      },
      "sources": [
        {
          "label": "Wikipedia — 1581",
          "url": "https://en.wikipedia.org/wiki/1581"
        }
      ],
      "ruler": null,
      "sparse_data": true,
      "raw_score": 60
    },
    "spanish_philippines": {
      "score": 87,
      "summary": "Brecke records no major conflicts touching this region in 1581 (safety scored at the era baseline of 85). No Maddison GDP coverage for this region — economy held at neutral 50, reflecting the thin pre-modern record outside the European core. Governance held at neutral (V-Dem coverage starts 1789).",
      "factors": {
        "safety": 85,
        "health": 45,
        "economy": 50,
        "governance": 50,
        "religious_tolerance": 50
      },
      "factor_sources": {
        "safety": "brecke",
        "health": "baseline",
        "economy": "neutral",
        "governance": "neutral",
        "religious_tolerance": "neutral"
      },
      "sources": [
        {
          "label": "Wikipedia — 1581",
          "url": "https://en.wikipedia.org/wiki/1581"
        }
      ],
      "ruler": null,
      "sparse_data": true,
      "raw_score": 60
    },
    "kongo_angola": {
      "score": 74,
      "summary": "Active conflicts in 1581: Ndongo-Portugal (Angola), 1579-85. No Maddison GDP coverage for this region — economy held at neutral 50, reflecting the thin pre-modern record outside the European core. Governance held at neutral (V-Dem coverage starts 1789).",
      "factors": {
        "safety": 73,
        "health": 45,
        "economy": 50,
        "governance": 50,
        "religious_tolerance": 50
      },
      "factor_sources": {
        "safety": "brecke",
        "health": "baseline",
        "economy": "neutral",
        "governance": "neutral",
        "religious_tolerance": "neutral"
      },
      "sources": [
        {
          "label": "Brecke Conflict Catalog 1400-2000",
          "url": "https://brecke.inta.gatech.edu/research/conflict/"
        },
        {
          "label": "Wikipedia — 1581",
          "url": "https://en.wikipedia.org/wiki/1581"
        }
      ],
      "ruler": null,
      "sparse_data": true,
      "raw_score": 56
    },
    "southern_africa": {
      "score": 87,
      "summary": "Brecke records no major conflicts touching this region in 1581 (safety scored at the era baseline of 85). No Maddison GDP coverage for this region — economy held at neutral 50, reflecting the thin pre-modern record outside the European core. Governance held at neutral (V-Dem coverage starts 1789).",
      "factors": {
        "safety": 85,
        "health": 45,
        "economy": 50,
        "governance": 50,
        "religious_tolerance": 50
      },
      "factor_sources": {
        "safety": "brecke",
        "health": "baseline",
        "economy": "neutral",
        "governance": "neutral",
        "religious_tolerance": "neutral"
      },
      "sources": [
        {
          "label": "Wikipedia — 1581",
          "url": "https://en.wikipedia.org/wiki/1581"
        }
      ],
      "ruler": null,
      "sparse_data": true,
      "raw_score": 60
    },
    "asante_coast": {
      "score": 87,
      "summary": "Brecke records no major conflicts touching this region in 1581 (safety scored at the era baseline of 85). No Maddison GDP coverage for this region — economy held at neutral 50, reflecting the thin pre-modern record outside the European core. Governance held at neutral (V-Dem coverage starts 1789).",
      "factors": {
        "safety": 85,
        "health": 45,
        "economy": 50,
        "governance": 50,
        "religious_tolerance": 50
      },
      "factor_sources": {
        "safety": "brecke",
        "health": "baseline",
        "economy": "neutral",
        "governance": "neutral",
        "religious_tolerance": "neutral"
      },
      "sources": [
        {
          "label": "Wikipedia — 1581",
          "url": "https://en.wikipedia.org/wiki/1581"
        }
      ],
      "ruler": null,
      "sparse_data": true,
      "raw_score": 60
    },
    "sahel_interior": {
      "score": 87,
      "summary": "Brecke records no major conflicts touching this region in 1581 (safety scored at the era baseline of 85). No Maddison GDP coverage for this region — economy held at neutral 50, reflecting the thin pre-modern record outside the European core. Governance held at neutral (V-Dem coverage starts 1789).",
      "factors": {
        "safety": 85,
        "health": 45,
        "economy": 50,
        "governance": 50,
        "religious_tolerance": 50
      },
      "factor_sources": {
        "safety": "brecke",
        "health": "baseline",
        "economy": "neutral",
        "governance": "neutral",
        "religious_tolerance": "neutral"
      },
      "sources": [
        {
          "label": "Wikipedia — 1581",
          "url": "https://en.wikipedia.org/wiki/1581"
        }
      ],
      "ruler": null,
      "sparse_data": true,
      "raw_score": 60
    },
    "new_spain": {
      "score": 87,
      "summary": "Brecke records no major conflicts touching this region in 1581 (safety scored at the era baseline of 85). No Maddison GDP coverage for this region — economy held at neutral 50, reflecting the thin pre-modern record outside the European core. Governance held at neutral (V-Dem coverage starts 1789).",
      "factors": {
        "safety": 85,
        "health": 45,
        "economy": 50,
        "governance": 50,
        "religious_tolerance": 50
      },
      "factor_sources": {
        "safety": "brecke",
        "health": "baseline",
        "economy": "neutral",
        "governance": "neutral",
        "religious_tolerance": "neutral"
      },
      "sources": [
        {
          "label": "Wikipedia — 1581",
          "url": "https://en.wikipedia.org/wiki/1581"
        }
      ],
      "ruler": null,
      "sparse_data": true,
      "raw_score": 60
    },
    "caribbean": {
      "score": 87,
      "summary": "Brecke records no major conflicts touching this region in 1581 (safety scored at the era baseline of 85). No Maddison GDP coverage for this region — economy held at neutral 50, reflecting the thin pre-modern record outside the European core. Governance held at neutral (V-Dem coverage starts 1789).",
      "factors": {
        "safety": 85,
        "health": 45,
        "economy": 50,
        "governance": 50,
        "religious_tolerance": 50
      },
      "factor_sources": {
        "safety": "brecke",
        "health": "baseline",
        "economy": "neutral",
        "governance": "neutral",
        "religious_tolerance": "neutral"
      },
      "sources": [
        {
          "label": "Wikipedia — 1581",
          "url": "https://en.wikipedia.org/wiki/1581"
        }
      ],
      "ruler": null,
      "sparse_data": true,
      "raw_score": 60
    }
  }
}