{
  "year": 1715,
  "label": "1715 CE",
  "region_set": "early_modern",
  "era_summary": "1715 (MDCCXV) was a common year starting on Tuesday of the Gregorian calendar and a common year starting on Saturday of the Julian calendar, the 1715th year of the Common Era (CE) and Anno Domini (AD) designations, the 715th year of the 2nd millennium, the 15th year of the 18th century, and the 6th year of the 1710s decade. As of the start of 1715, the Gregorian calendar was 11 days ahead of the Julian calendar, which remained in localized use until 1923. ",
  "regions": {
    "rome_italy": {
      "score": 64,
      "summary": "Active conflicts in 1715: Venice-Turkey, 1714-18. No Maddison GDP coverage for this region — economy held at neutral 50, reflecting the thin pre-modern record outside the European core. Governance held at neutral (V-Dem coverage starts 1789).",
      "factors": {
        "safety": 73,
        "health": 45,
        "economy": 50,
        "governance": 50,
        "religious_tolerance": 50
      },
      "factor_sources": {
        "safety": "brecke",
        "health": "baseline",
        "economy": "neutral",
        "governance": "neutral",
        "religious_tolerance": "neutral"
      },
      "sources": [
        {
          "label": "Brecke Conflict Catalog 1400-2000",
          "url": "https://brecke.inta.gatech.edu/research/conflict/"
        },
        {
          "label": "Wikipedia — 1715",
          "url": "https://en.wikipedia.org/wiki/1715"
        }
      ],
      "ruler": null,
      "sparse_data": true,
      "raw_score": 56
    },
    "andalusia_iberia": {
      "score": 64,
      "summary": "Active conflicts in 1715: Spain (Catalonia), 1705-15. Maddison records GDP/capita 1613 (PRT, 1715) — used as the economy proxy for the whole region. Governance held at neutral (V-Dem coverage starts 1789).",
      "factors": {
        "safety": 73,
        "health": 45,
        "economy": 51,
        "governance": 50,
        "religious_tolerance": 50
      },
      "factor_sources": {
        "safety": "brecke",
        "health": "baseline",
        "economy": "maddison",
        "governance": "neutral",
        "religious_tolerance": "neutral"
      },
      "sources": [
        {
          "label": "Brecke Conflict Catalog 1400-2000",
          "url": "https://brecke.inta.gatech.edu/research/conflict/"
        },
        {
          "label": "Maddison Project 2023 — PRT 1715 gdppc=1613",
          "url": "https://www.rug.nl/ggdc/historicaldevelopment/maddison/releases/maddison-project-database-2023"
        },
        {
          "label": "Wikipedia — 1715",
          "url": "https://en.wikipedia.org/wiki/1715"
        }
      ],
      "ruler": null,
      "sparse_data": true,
      "raw_score": 56
    },
    "francia": {
      "score": 96,
      "summary": "Active conflicts in 1715: Algiers-United Provinces, 1715-26. Maddison records GDP/capita 3793 (NLD, 1715) — used as the economy proxy for the whole region. Governance held at neutral (V-Dem coverage starts 1789).",
      "factors": {
        "safety": 73,
        "health": 45,
        "economy": 90,
        "governance": 50,
        "religious_tolerance": 50
      },
      "factor_sources": {
        "safety": "brecke",
        "health": "baseline",
        "economy": "maddison",
        "governance": "neutral",
        "religious_tolerance": "neutral"
      },
      "sources": [
        {
          "label": "Brecke Conflict Catalog 1400-2000",
          "url": "https://brecke.inta.gatech.edu/research/conflict/"
        },
        {
          "label": "Maddison Project 2023 — NLD 1715 gdppc=3793",
          "url": "https://www.rug.nl/ggdc/historicaldevelopment/maddison/releases/maddison-project-database-2023"
        },
        {
          "label": "Wikipedia — 1715",
          "url": "https://en.wikipedia.org/wiki/1715"
        }
      ],
      "ruler": null,
      "sparse_data": true,
      "raw_score": 64
    },
    "england": {
      "score": 33,
      "summary": "Active conflicts in 1715: Denmark, Saxony, Poland, Russia, Prussia, Hanover, Britain-Sweden, Turkey, 1700-21; Britain-Sweden, 1715-19; Britain (Scotland), 1715-16. Maddison records GDP/capita 2294 (GBR, 1715) — used as the economy proxy for the whole region. Governance held at neutral (V-Dem coverage starts 1789).",
      "factors": {
        "safety": 24,
        "health": 45,
        "economy": 84,
        "governance": 50,
        "religious_tolerance": 50
      },
      "factor_sources": {
        "safety": "brecke",
        "health": "baseline",
        "economy": "maddison",
        "governance": "neutral",
        "religious_tolerance": "neutral"
      },
      "sources": [
        {
          "label": "Brecke Conflict Catalog 1400-2000",
          "url": "https://brecke.inta.gatech.edu/research/conflict/"
        },
        {
          "label": "Maddison Project 2023 — GBR 1715 gdppc=2294",
          "url": "https://www.rug.nl/ggdc/historicaldevelopment/maddison/releases/maddison-project-database-2023"
        },
        {
          "label": "Wikipedia — 1715",
          "url": "https://en.wikipedia.org/wiki/1715"
        }
      ],
      "ruler": null,
      "sparse_data": true,
      "raw_score": 48
    },
    "rus": {
      "score": 21,
      "summary": "Active conflicts in 1715: Denmark, Saxony, Poland, Russia, Prussia, Hanover, Britain-Sweden, Turkey, 1700-21; Russia-Koraks (Kamchatka), 1708-15; Prussia-Sweden, 1715-20. No Maddison GDP coverage for this region — economy held at neutral 50, reflecting the thin pre-modern record outside the European core. Governance held at neutral (V-Dem coverage starts 1789).",
      "factors": {
        "safety": 36,
        "health": 45,
        "economy": 50,
        "governance": 50,
        "religious_tolerance": 50
      },
      "factor_sources": {
        "safety": "brecke",
        "health": "baseline",
        "economy": "neutral",
        "governance": "neutral",
        "religious_tolerance": "neutral"
      },
      "sources": [
        {
          "label": "Brecke Conflict Catalog 1400-2000",
          "url": "https://brecke.inta.gatech.edu/research/conflict/"
        },
        {
          "label": "Wikipedia — 1715",
          "url": "https://en.wikipedia.org/wiki/1715"
        }
      ],
      "ruler": null,
      "sparse_data": true,
      "raw_score": 45
    },
    "constantinople_balkans": {
      "score": 37,
      "summary": "Active conflicts in 1715: Denmark, Saxony, Poland, Russia, Prussia, Hanover, Britain-Sweden, Turkey, 1700-21; Venice-Turkey, 1714-18. No Maddison GDP coverage for this region — economy held at neutral 50, reflecting the thin pre-modern record outside the European core. Governance held at neutral (V-Dem coverage starts 1789).",
      "factors": {
        "safety": 48,
        "health": 45,
        "economy": 50,
        "governance": 50,
        "religious_tolerance": 50
      },
      "factor_sources": {
        "safety": "brecke",
        "health": "baseline",
        "economy": "neutral",
        "governance": "neutral",
        "religious_tolerance": "neutral"
      },
      "sources": [
        {
          "label": "Brecke Conflict Catalog 1400-2000",
          "url": "https://brecke.inta.gatech.edu/research/conflict/"
        },
        {
          "label": "Wikipedia — 1715",
          "url": "https://en.wikipedia.org/wiki/1715"
        }
      ],
      "ruler": null,
      "sparse_data": true,
      "raw_score": 49
    },
    "persia": {
      "score": 80,
      "summary": "Brecke records no major conflicts touching this region in 1715 (safety scored at the era baseline of 85). No Maddison GDP coverage for this region — economy held at neutral 50, reflecting the thin pre-modern record outside the European core. Governance held at neutral (V-Dem coverage starts 1789).",
      "factors": {
        "safety": 85,
        "health": 45,
        "economy": 50,
        "governance": 50,
        "religious_tolerance": 50
      },
      "factor_sources": {
        "safety": "brecke",
        "health": "baseline",
        "economy": "neutral",
        "governance": "neutral",
        "religious_tolerance": "neutral"
      },
      "sources": [
        {
          "label": "Wikipedia — 1715",
          "url": "https://en.wikipedia.org/wiki/1715"
        }
      ],
      "ruler": null,
      "sparse_data": true,
      "raw_score": 60
    },
    "central_asia": {
      "score": 80,
      "summary": "Brecke records no major conflicts touching this region in 1715 (safety scored at the era baseline of 85). No Maddison GDP coverage for this region — economy held at neutral 50, reflecting the thin pre-modern record outside the European core. Governance held at neutral (V-Dem coverage starts 1789).",
      "factors": {
        "safety": 85,
        "health": 45,
        "economy": 50,
        "governance": 50,
        "religious_tolerance": 50
      },
      "factor_sources": {
        "safety": "brecke",
        "health": "baseline",
        "economy": "neutral",
        "governance": "neutral",
        "religious_tolerance": "neutral"
      },
      "sources": [
        {
          "label": "Wikipedia — 1715",
          "url": "https://en.wikipedia.org/wiki/1715"
        }
      ],
      "ruler": null,
      "sparse_data": true,
      "raw_score": 60
    },
    "egypt_nile": {
      "score": 80,
      "summary": "Brecke records no major conflicts touching this region in 1715 (safety scored at the era baseline of 85). No Maddison GDP coverage for this region — economy held at neutral 50, reflecting the thin pre-modern record outside the European core. Governance held at neutral (V-Dem coverage starts 1789).",
      "factors": {
        "safety": 85,
        "health": 45,
        "economy": 50,
        "governance": 50,
        "religious_tolerance": 50
      },
      "factor_sources": {
        "safety": "brecke",
        "health": "baseline",
        "economy": "neutral",
        "governance": "neutral",
        "religious_tolerance": "neutral"
      },
      "sources": [
        {
          "label": "Wikipedia — 1715",
          "url": "https://en.wikipedia.org/wiki/1715"
        }
      ],
      "ruler": null,
      "sparse_data": true,
      "raw_score": 60
    },
    "arabia": {
      "score": 80,
      "summary": "Brecke records no major conflicts touching this region in 1715 (safety scored at the era baseline of 85). No Maddison GDP coverage for this region — economy held at neutral 50, reflecting the thin pre-modern record outside the European core. Governance held at neutral (V-Dem coverage starts 1789).",
      "factors": {
        "safety": 85,
        "health": 45,
        "economy": 50,
        "governance": 50,
        "religious_tolerance": 50
      },
      "factor_sources": {
        "safety": "brecke",
        "health": "baseline",
        "economy": "neutral",
        "governance": "neutral",
        "religious_tolerance": "neutral"
      },
      "sources": [
        {
          "label": "Wikipedia — 1715",
          "url": "https://en.wikipedia.org/wiki/1715"
        }
      ],
      "ruler": null,
      "sparse_data": true,
      "raw_score": 60
    },
    "ethiopia": {
      "score": 80,
      "summary": "Brecke records no major conflicts touching this region in 1715 (safety scored at the era baseline of 85). No Maddison GDP coverage for this region — economy held at neutral 50, reflecting the thin pre-modern record outside the European core. Governance held at neutral (V-Dem coverage starts 1789).",
      "factors": {
        "safety": 85,
        "health": 45,
        "economy": 50,
        "governance": 50,
        "religious_tolerance": 50
      },
      "factor_sources": {
        "safety": "brecke",
        "health": "baseline",
        "economy": "neutral",
        "governance": "neutral",
        "religious_tolerance": "neutral"
      },
      "sources": [
        {
          "label": "Wikipedia — 1715",
          "url": "https://en.wikipedia.org/wiki/1715"
        }
      ],
      "ruler": null,
      "sparse_data": true,
      "raw_score": 60
    },
    "han_china": {
      "score": 80,
      "summary": "Brecke records no major conflicts touching this region in 1715 (safety scored at the era baseline of 85). No Maddison GDP coverage for this region — economy held at neutral 50, reflecting the thin pre-modern record outside the European core. Governance held at neutral (V-Dem coverage starts 1789).",
      "factors": {
        "safety": 85,
        "health": 45,
        "economy": 50,
        "governance": 50,
        "religious_tolerance": 50
      },
      "factor_sources": {
        "safety": "brecke",
        "health": "baseline",
        "economy": "neutral",
        "governance": "neutral",
        "religious_tolerance": "neutral"
      },
      "sources": [
        {
          "label": "Wikipedia — 1715",
          "url": "https://en.wikipedia.org/wiki/1715"
        }
      ],
      "ruler": null,
      "sparse_data": true,
      "raw_score": 60
    },
    "japan": {
      "score": 80,
      "summary": "Brecke records no major conflicts touching this region in 1715 (safety scored at the era baseline of 85). No Maddison GDP coverage for this region — economy held at neutral 50, reflecting the thin pre-modern record outside the European core. Governance held at neutral (V-Dem coverage starts 1789).",
      "factors": {
        "safety": 85,
        "health": 45,
        "economy": 50,
        "governance": 50,
        "religious_tolerance": 50
      },
      "factor_sources": {
        "safety": "brecke",
        "health": "baseline",
        "economy": "neutral",
        "governance": "neutral",
        "religious_tolerance": "neutral"
      },
      "sources": [
        {
          "label": "Wikipedia — 1715",
          "url": "https://en.wikipedia.org/wiki/1715"
        }
      ],
      "ruler": null,
      "sparse_data": true,
      "raw_score": 60
    },
    "north_america_east": {
      "score": 64,
      "summary": "Active conflicts in 1715: American settlers-Indians (S. Carolina), 1715. No Maddison GDP coverage for this region — economy held at neutral 50, reflecting the thin pre-modern record outside the European core. Governance held at neutral (V-Dem coverage starts 1789).",
      "factors": {
        "safety": 73,
        "health": 45,
        "economy": 50,
        "governance": 50,
        "religious_tolerance": 50
      },
      "factor_sources": {
        "safety": "brecke",
        "health": "baseline",
        "economy": "neutral",
        "governance": "neutral",
        "religious_tolerance": "neutral"
      },
      "sources": [
        {
          "label": "Brecke Conflict Catalog 1400-2000",
          "url": "https://brecke.inta.gatech.edu/research/conflict/"
        },
        {
          "label": "Wikipedia — 1715",
          "url": "https://en.wikipedia.org/wiki/1715"
        }
      ],
      "ruler": null,
      "sparse_data": true,
      "raw_score": 56
    },
    "andes": {
      "score": 64,
      "summary": "Brecke records no major conflicts touching this region in 1715 (safety scored at the era baseline of 85). Maddison records GDP/capita 1060 (PER, 1715) — used as the economy proxy for the whole region. Governance held at neutral (V-Dem coverage starts 1789).",
      "factors": {
        "safety": 85,
        "health": 45,
        "economy": 32,
        "governance": 50,
        "religious_tolerance": 50
      },
      "factor_sources": {
        "safety": "brecke",
        "health": "baseline",
        "economy": "maddison",
        "governance": "neutral",
        "religious_tolerance": "neutral"
      },
      "sources": [
        {
          "label": "Maddison Project 2023 — PER 1715 gdppc=1060",
          "url": "https://www.rug.nl/ggdc/historicaldevelopment/maddison/releases/maddison-project-database-2023"
        },
        {
          "label": "Wikipedia — 1715",
          "url": "https://en.wikipedia.org/wiki/1715"
        }
      ],
      "ruler": null,
      "sparse_data": true,
      "raw_score": 56
    },
    "brazil_amazon": {
      "score": 80,
      "summary": "Brecke records no major conflicts touching this region in 1715 (safety scored at the era baseline of 85). No Maddison GDP coverage for this region — economy held at neutral 50, reflecting the thin pre-modern record outside the European core. Governance held at neutral (V-Dem coverage starts 1789).",
      "factors": {
        "safety": 85,
        "health": 45,
        "economy": 50,
        "governance": 50,
        "religious_tolerance": 50
      },
      "factor_sources": {
        "safety": "brecke",
        "health": "baseline",
        "economy": "neutral",
        "governance": "neutral",
        "religious_tolerance": "neutral"
      },
      "sources": [
        {
          "label": "Wikipedia — 1715",
          "url": "https://en.wikipedia.org/wiki/1715"
        }
      ],
      "ruler": null,
      "sparse_data": true,
      "raw_score": 60
    },
    "sweden_empire": {
      "score": 9,
      "summary": "Active conflicts in 1715: Denmark, Saxony, Poland, Russia, Prussia, Hanover, Britain-Sweden, Turkey, 1700-21; Sweden-Saxony, Poland, 1709-19; Sweden-Denmark, 1709-20. Maddison records GDP/capita 1980 (SWE, 1715) — used as the economy proxy for the whole region. Governance held at neutral (V-Dem coverage starts 1789).",
      "factors": {
        "safety": 12,
        "health": 45,
        "economy": 70,
        "governance": 50,
        "religious_tolerance": 50
      },
      "factor_sources": {
        "safety": "brecke",
        "health": "baseline",
        "economy": "maddison",
        "governance": "neutral",
        "religious_tolerance": "neutral"
      },
      "sources": [
        {
          "label": "Brecke Conflict Catalog 1400-2000",
          "url": "https://brecke.inta.gatech.edu/research/conflict/"
        },
        {
          "label": "Maddison Project 2023 — SWE 1715 gdppc=1980",
          "url": "https://www.rug.nl/ggdc/historicaldevelopment/maddison/releases/maddison-project-database-2023"
        },
        {
          "label": "Wikipedia — 1715",
          "url": "https://en.wikipedia.org/wiki/1715"
        }
      ],
      "ruler": null,
      "sparse_data": true,
      "raw_score": 42
    },
    "denmark_norway": {
      "score": 37,
      "summary": "Active conflicts in 1715: Denmark, Saxony, Poland, Russia, Prussia, Hanover, Britain-Sweden, Turkey, 1700-21; Sweden-Denmark, 1709-20. No Maddison GDP coverage for this region — economy held at neutral 50, reflecting the thin pre-modern record outside the European core. Governance held at neutral (V-Dem coverage starts 1789).",
      "factors": {
        "safety": 48,
        "health": 45,
        "economy": 50,
        "governance": 50,
        "religious_tolerance": 50
      },
      "factor_sources": {
        "safety": "brecke",
        "health": "baseline",
        "economy": "neutral",
        "governance": "neutral",
        "religious_tolerance": "neutral"
      },
      "sources": [
        {
          "label": "Brecke Conflict Catalog 1400-2000",
          "url": "https://brecke.inta.gatech.edu/research/conflict/"
        },
        {
          "label": "Wikipedia — 1715",
          "url": "https://en.wikipedia.org/wiki/1715"
        }
      ],
      "ruler": null,
      "sparse_data": true,
      "raw_score": 49
    },
    "swedish_baltic": {
      "score": 80,
      "summary": "Brecke records no major conflicts touching this region in 1715 (safety scored at the era baseline of 85). No Maddison GDP coverage for this region — economy held at neutral 50, reflecting the thin pre-modern record outside the European core. Governance held at neutral (V-Dem coverage starts 1789).",
      "factors": {
        "safety": 85,
        "health": 45,
        "economy": 50,
        "governance": 50,
        "religious_tolerance": 50
      },
      "factor_sources": {
        "safety": "brecke",
        "health": "baseline",
        "economy": "neutral",
        "governance": "neutral",
        "religious_tolerance": "neutral"
      },
      "sources": [
        {
          "label": "Wikipedia — 1715",
          "url": "https://en.wikipedia.org/wiki/1715"
        }
      ],
      "ruler": null,
      "sparse_data": true,
      "raw_score": 60
    },
    "habsburg_austria": {
      "score": 80,
      "summary": "Brecke records no major conflicts touching this region in 1715 (safety scored at the era baseline of 85). No Maddison GDP coverage for this region — economy held at neutral 50, reflecting the thin pre-modern record outside the European core. Governance held at neutral (V-Dem coverage starts 1789).",
      "factors": {
        "safety": 85,
        "health": 45,
        "economy": 50,
        "governance": 50,
        "religious_tolerance": 50
      },
      "factor_sources": {
        "safety": "brecke",
        "health": "baseline",
        "economy": "neutral",
        "governance": "neutral",
        "religious_tolerance": "neutral"
      },
      "sources": [
        {
          "label": "Wikipedia — 1715",
          "url": "https://en.wikipedia.org/wiki/1715"
        }
      ],
      "ruler": null,
      "sparse_data": true,
      "raw_score": 60
    },
    "prussia_brandenburg": {
      "score": 41,
      "summary": "Active conflicts in 1715: Denmark, Saxony, Poland, Russia, Prussia, Hanover, Britain-Sweden, Turkey, 1700-21; Prussia-Sweden, 1715-20. Maddison records GDP/capita 1663 (DEU, 1715) — used as the economy proxy for the whole region. Governance held at neutral (V-Dem coverage starts 1789).",
      "factors": {
        "safety": 48,
        "health": 45,
        "economy": 58,
        "governance": 50,
        "religious_tolerance": 50
      },
      "factor_sources": {
        "safety": "brecke",
        "health": "baseline",
        "economy": "maddison",
        "governance": "neutral",
        "religious_tolerance": "neutral"
      },
      "sources": [
        {
          "label": "Brecke Conflict Catalog 1400-2000",
          "url": "https://brecke.inta.gatech.edu/research/conflict/"
        },
        {
          "label": "Maddison Project 2023 — DEU 1715 gdppc=1663",
          "url": "https://www.rug.nl/ggdc/historicaldevelopment/maddison/releases/maddison-project-database-2023"
        },
        {
          "label": "Wikipedia — 1715",
          "url": "https://en.wikipedia.org/wiki/1715"
        }
      ],
      "ruler": null,
      "sparse_data": true,
      "raw_score": 50
    },
    "german_princes": {
      "score": 41,
      "summary": "Active conflicts in 1715: Denmark, Saxony, Poland, Russia, Prussia, Hanover, Britain-Sweden, Turkey, 1700-21; Sweden-Saxony, Poland, 1709-19. Maddison records GDP/capita 1663 (DEU, 1715) — used as the economy proxy for the whole region. Governance held at neutral (V-Dem coverage starts 1789).",
      "factors": {
        "safety": 48,
        "health": 45,
        "economy": 58,
        "governance": 50,
        "religious_tolerance": 50
      },
      "factor_sources": {
        "safety": "brecke",
        "health": "baseline",
        "economy": "maddison",
        "governance": "neutral",
        "religious_tolerance": "neutral"
      },
      "sources": [
        {
          "label": "Brecke Conflict Catalog 1400-2000",
          "url": "https://brecke.inta.gatech.edu/research/conflict/"
        },
        {
          "label": "Maddison Project 2023 — DEU 1715 gdppc=1663",
          "url": "https://www.rug.nl/ggdc/historicaldevelopment/maddison/releases/maddison-project-database-2023"
        },
        {
          "label": "Wikipedia — 1715",
          "url": "https://en.wikipedia.org/wiki/1715"
        }
      ],
      "ruler": null,
      "sparse_data": true,
      "raw_score": 50
    },
    "polish_lithuanian_commonwealth": {
      "score": 1,
      "summary": "Active conflicts in 1715: Denmark, Saxony, Poland, Russia, Prussia, Hanover, Britain-Sweden, Turkey, 1700-21; Sweden-Saxony, Poland, 1709-19; Poland, 1715-17. Maddison records GDP/capita 928 (POL, 1715) — used as the economy proxy for the whole region. Governance held at neutral (V-Dem coverage starts 1789).",
      "factors": {
        "safety": 36,
        "health": 45,
        "economy": 25,
        "governance": 50,
        "religious_tolerance": 50
      },
      "factor_sources": {
        "safety": "brecke",
        "health": "baseline",
        "economy": "maddison",
        "governance": "neutral",
        "religious_tolerance": "neutral"
      },
      "sources": [
        {
          "label": "Brecke Conflict Catalog 1400-2000",
          "url": "https://brecke.inta.gatech.edu/research/conflict/"
        },
        {
          "label": "Maddison Project 2023 — POL 1715 gdppc=928",
          "url": "https://www.rug.nl/ggdc/historicaldevelopment/maddison/releases/maddison-project-database-2023"
        },
        {
          "label": "Wikipedia — 1715",
          "url": "https://en.wikipedia.org/wiki/1715"
        }
      ],
      "ruler": null,
      "sparse_data": true,
      "raw_score": 40
    },
    "mughal_north": {
      "score": 80,
      "summary": "Brecke records no major conflicts touching this region in 1715 (safety scored at the era baseline of 85). No Maddison GDP coverage for this region — economy held at neutral 50, reflecting the thin pre-modern record outside the European core. Governance held at neutral (V-Dem coverage starts 1789).",
      "factors": {
        "safety": 85,
        "health": 45,
        "economy": 50,
        "governance": 50,
        "religious_tolerance": 50
      },
      "factor_sources": {
        "safety": "brecke",
        "health": "baseline",
        "economy": "neutral",
        "governance": "neutral",
        "religious_tolerance": "neutral"
      },
      "sources": [
        {
          "label": "Wikipedia — 1715",
          "url": "https://en.wikipedia.org/wiki/1715"
        }
      ],
      "ruler": null,
      "sparse_data": true,
      "raw_score": 60
    },
    "maratha_confederacy": {
      "score": 80,
      "summary": "Brecke records no major conflicts touching this region in 1715 (safety scored at the era baseline of 85). No Maddison GDP coverage for this region — economy held at neutral 50, reflecting the thin pre-modern record outside the European core. Governance held at neutral (V-Dem coverage starts 1789).",
      "factors": {
        "safety": 85,
        "health": 45,
        "economy": 50,
        "governance": 50,
        "religious_tolerance": 50
      },
      "factor_sources": {
        "safety": "brecke",
        "health": "baseline",
        "economy": "neutral",
        "governance": "neutral",
        "religious_tolerance": "neutral"
      },
      "sources": [
        {
          "label": "Wikipedia — 1715",
          "url": "https://en.wikipedia.org/wiki/1715"
        }
      ],
      "ruler": null,
      "sparse_data": true,
      "raw_score": 60
    },
    "bengal": {
      "score": 80,
      "summary": "Brecke records no major conflicts touching this region in 1715 (safety scored at the era baseline of 85). No Maddison GDP coverage for this region — economy held at neutral 50, reflecting the thin pre-modern record outside the European core. Governance held at neutral (V-Dem coverage starts 1789).",
      "factors": {
        "safety": 85,
        "health": 45,
        "economy": 50,
        "governance": 50,
        "religious_tolerance": 50
      },
      "factor_sources": {
        "safety": "brecke",
        "health": "baseline",
        "economy": "neutral",
        "governance": "neutral",
        "religious_tolerance": "neutral"
      },
      "sources": [
        {
          "label": "Wikipedia — 1715",
          "url": "https://en.wikipedia.org/wiki/1715"
        }
      ],
      "ruler": null,
      "sparse_data": true,
      "raw_score": 60
    },
    "deccan_sultanates": {
      "score": 80,
      "summary": "Brecke records no major conflicts touching this region in 1715 (safety scored at the era baseline of 85). No Maddison GDP coverage for this region — economy held at neutral 50, reflecting the thin pre-modern record outside the European core. Governance held at neutral (V-Dem coverage starts 1789).",
      "factors": {
        "safety": 85,
        "health": 45,
        "economy": 50,
        "governance": 50,
        "religious_tolerance": 50
      },
      "factor_sources": {
        "safety": "brecke",
        "health": "baseline",
        "economy": "neutral",
        "governance": "neutral",
        "religious_tolerance": "neutral"
      },
      "sources": [
        {
          "label": "Wikipedia — 1715",
          "url": "https://en.wikipedia.org/wiki/1715"
        }
      ],
      "ruler": null,
      "sparse_data": true,
      "raw_score": 60
    },
    "voc_indonesia": {
      "score": 80,
      "summary": "Brecke records no major conflicts touching this region in 1715 (safety scored at the era baseline of 85). No Maddison GDP coverage for this region — economy held at neutral 50, reflecting the thin pre-modern record outside the European core. Governance held at neutral (V-Dem coverage starts 1789).",
      "factors": {
        "safety": 85,
        "health": 45,
        "economy": 50,
        "governance": 50,
        "religious_tolerance": 50
      },
      "factor_sources": {
        "safety": "brecke",
        "health": "baseline",
        "economy": "neutral",
        "governance": "neutral",
        "religious_tolerance": "neutral"
      },
      "sources": [
        {
          "label": "Wikipedia — 1715",
          "url": "https://en.wikipedia.org/wiki/1715"
        }
      ],
      "ruler": null,
      "sparse_data": true,
      "raw_score": 60
    },
    "siam_vietnam_burma": {
      "score": 80,
      "summary": "Brecke records no major conflicts touching this region in 1715 (safety scored at the era baseline of 85). No Maddison GDP coverage for this region — economy held at neutral 50, reflecting the thin pre-modern record outside the European core. Governance held at neutral (V-Dem coverage starts 1789).",
      "factors": {
        "safety": 85,
        "health": 45,
        "economy": 50,
        "governance": 50,
        "religious_tolerance": 50
      },
      "factor_sources": {
        "safety": "brecke",
        "health": "baseline",
        "economy": "neutral",
        "governance": "neutral",
        "religious_tolerance": "neutral"
      },
      "sources": [
        {
          "label": "Wikipedia — 1715",
          "url": "https://en.wikipedia.org/wiki/1715"
        }
      ],
      "ruler": null,
      "sparse_data": true,
      "raw_score": 60
    },
    "spanish_philippines": {
      "score": 80,
      "summary": "Brecke records no major conflicts touching this region in 1715 (safety scored at the era baseline of 85). No Maddison GDP coverage for this region — economy held at neutral 50, reflecting the thin pre-modern record outside the European core. Governance held at neutral (V-Dem coverage starts 1789).",
      "factors": {
        "safety": 85,
        "health": 45,
        "economy": 50,
        "governance": 50,
        "religious_tolerance": 50
      },
      "factor_sources": {
        "safety": "brecke",
        "health": "baseline",
        "economy": "neutral",
        "governance": "neutral",
        "religious_tolerance": "neutral"
      },
      "sources": [
        {
          "label": "Wikipedia — 1715",
          "url": "https://en.wikipedia.org/wiki/1715"
        }
      ],
      "ruler": null,
      "sparse_data": true,
      "raw_score": 60
    },
    "kongo_angola": {
      "score": 80,
      "summary": "Brecke records no major conflicts touching this region in 1715 (safety scored at the era baseline of 85). No Maddison GDP coverage for this region — economy held at neutral 50, reflecting the thin pre-modern record outside the European core. Governance held at neutral (V-Dem coverage starts 1789).",
      "factors": {
        "safety": 85,
        "health": 45,
        "economy": 50,
        "governance": 50,
        "religious_tolerance": 50
      },
      "factor_sources": {
        "safety": "brecke",
        "health": "baseline",
        "economy": "neutral",
        "governance": "neutral",
        "religious_tolerance": "neutral"
      },
      "sources": [
        {
          "label": "Wikipedia — 1715",
          "url": "https://en.wikipedia.org/wiki/1715"
        }
      ],
      "ruler": null,
      "sparse_data": true,
      "raw_score": 60
    },
    "southern_africa": {
      "score": 100,
      "summary": "Brecke records no major conflicts touching this region in 1715 (safety scored at the era baseline of 85). Maddison records GDP/capita 2284 (ZAF, 1715) — used as the economy proxy for the whole region. Governance held at neutral (V-Dem coverage starts 1789).",
      "factors": {
        "safety": 85,
        "health": 45,
        "economy": 77,
        "governance": 50,
        "religious_tolerance": 50
      },
      "factor_sources": {
        "safety": "brecke",
        "health": "baseline",
        "economy": "maddison",
        "governance": "neutral",
        "religious_tolerance": "neutral"
      },
      "sources": [
        {
          "label": "Maddison Project 2023 — ZAF 1715 gdppc=2284",
          "url": "https://www.rug.nl/ggdc/historicaldevelopment/maddison/releases/maddison-project-database-2023"
        },
        {
          "label": "Wikipedia — 1715",
          "url": "https://en.wikipedia.org/wiki/1715"
        }
      ],
      "ruler": null,
      "sparse_data": true,
      "raw_score": 65
    },
    "asante_coast": {
      "score": 80,
      "summary": "Brecke records no major conflicts touching this region in 1715 (safety scored at the era baseline of 85). No Maddison GDP coverage for this region — economy held at neutral 50, reflecting the thin pre-modern record outside the European core. Governance held at neutral (V-Dem coverage starts 1789).",
      "factors": {
        "safety": 85,
        "health": 45,
        "economy": 50,
        "governance": 50,
        "religious_tolerance": 50
      },
      "factor_sources": {
        "safety": "brecke",
        "health": "baseline",
        "economy": "neutral",
        "governance": "neutral",
        "religious_tolerance": "neutral"
      },
      "sources": [
        {
          "label": "Wikipedia — 1715",
          "url": "https://en.wikipedia.org/wiki/1715"
        }
      ],
      "ruler": null,
      "sparse_data": true,
      "raw_score": 60
    },
    "sahel_interior": {
      "score": 80,
      "summary": "Brecke records no major conflicts touching this region in 1715 (safety scored at the era baseline of 85). No Maddison GDP coverage for this region — economy held at neutral 50, reflecting the thin pre-modern record outside the European core. Governance held at neutral (V-Dem coverage starts 1789).",
      "factors": {
        "safety": 85,
        "health": 45,
        "economy": 50,
        "governance": 50,
        "religious_tolerance": 50
      },
      "factor_sources": {
        "safety": "brecke",
        "health": "baseline",
        "economy": "neutral",
        "governance": "neutral",
        "religious_tolerance": "neutral"
      },
      "sources": [
        {
          "label": "Wikipedia — 1715",
          "url": "https://en.wikipedia.org/wiki/1715"
        }
      ],
      "ruler": null,
      "sparse_data": true,
      "raw_score": 60
    },
    "new_spain": {
      "score": 76,
      "summary": "Brecke records no major conflicts touching this region in 1715 (safety scored at the era baseline of 85). Maddison records GDP/capita 1510 (MEX, 1715) — used as the economy proxy for the whole region. Governance held at neutral (V-Dem coverage starts 1789).",
      "factors": {
        "safety": 85,
        "health": 45,
        "economy": 44,
        "governance": 50,
        "religious_tolerance": 50
      },
      "factor_sources": {
        "safety": "brecke",
        "health": "baseline",
        "economy": "maddison",
        "governance": "neutral",
        "religious_tolerance": "neutral"
      },
      "sources": [
        {
          "label": "Maddison Project 2023 — MEX 1715 gdppc=1510",
          "url": "https://www.rug.nl/ggdc/historicaldevelopment/maddison/releases/maddison-project-database-2023"
        },
        {
          "label": "Wikipedia — 1715",
          "url": "https://en.wikipedia.org/wiki/1715"
        }
      ],
      "ruler": null,
      "sparse_data": true,
      "raw_score": 59
    },
    "caribbean": {
      "score": 80,
      "summary": "Brecke records no major conflicts touching this region in 1715 (safety scored at the era baseline of 85). No Maddison GDP coverage for this region — economy held at neutral 50, reflecting the thin pre-modern record outside the European core. Governance held at neutral (V-Dem coverage starts 1789).",
      "factors": {
        "safety": 85,
        "health": 45,
        "economy": 50,
        "governance": 50,
        "religious_tolerance": 50
      },
      "factor_sources": {
        "safety": "brecke",
        "health": "baseline",
        "economy": "neutral",
        "governance": "neutral",
        "religious_tolerance": "neutral"
      },
      "sources": [
        {
          "label": "Wikipedia — 1715",
          "url": "https://en.wikipedia.org/wiki/1715"
        }
      ],
      "ruler": null,
      "sparse_data": true,
      "raw_score": 60
    }
  }
}